Metadata-Version: 1.0
Name: lovely.essequence
Version: 0.1.0
Summary: a persistent sequence generator for elasticsearch
Home-page: http://github.com/lovelysystems/lovely.essequence
Author: lovelysystems
Author-email: office@lovelysystems.com
License: UNKNOWN
Platform: UNKNOWN
